CHANGES.rst
MANIFEST.in
README.rst
setup.py
bin/BarTracker
bin/BeatDetector
bin/BeatTracker
bin/CNNChordRecognition
bin/CNNOnsetDetector
bin/CRFBeatDetector
bin/ComplexFlux
bin/DBNBeatTracker
bin/DBNDownBeatTracker
bin/DCChordRecognition
bin/GMMPatternTracker
bin/KeyRecognition
bin/LogFiltSpecFlux
bin/MMBeatTracker
bin/OnsetDetector
bin/OnsetDetectorLL
bin/PianoTranscriptor
bin/PickleProcessor
bin/SpectralOnsetDetection
bin/SuperFlux
bin/SuperFluxNN
bin/TempoDetector
bin/evaluate
madmom/__init__.py
madmom/conftest.py
madmom/processors.py
madmom.egg-info/PKG-INFO
madmom.egg-info/SOURCES.txt
madmom.egg-info/dependency_links.txt
madmom.egg-info/requires.txt
madmom.egg-info/top_level.txt
madmom/audio/__init__.py
madmom/audio/chroma.py
madmom/audio/comb_filters.c
madmom/audio/filters.py
madmom/audio/signal.py
madmom/audio/spectrogram.py
madmom/audio/stft.py
madmom/evaluation/__init__.py
madmom/evaluation/beats.py
madmom/evaluation/chords.py
madmom/evaluation/key.py
madmom/evaluation/notes.py
madmom/evaluation/onsets.py
madmom/evaluation/tempo.py
madmom/features/__init__.py
madmom/features/beats.py
madmom/features/beats_crf.c
madmom/features/beats_hmm.py
madmom/features/chords.py
madmom/features/downbeats.py
madmom/features/key.py
madmom/features/notes.py
madmom/features/onsets.py
madmom/features/tempo.py
madmom/io/__init__.py
madmom/io/audio.py
madmom/io/midi.py
madmom/ml/__init__.py
madmom/ml/crf.py
madmom/ml/gmm.py
madmom/ml/hmm.c
madmom/ml/nn/__init__.py
madmom/ml/nn/activations.py
madmom/ml/nn/layers.c
madmom/ml/nn/layers.py
madmom/models/LICENSE
madmom/models/README.rst
madmom/models/__init__.py
madmom/models/beats/2015/beats_blstm_1.pkl
madmom/models/beats/2015/beats_blstm_2.pkl
madmom/models/beats/2015/beats_blstm_3.pkl
madmom/models/beats/2015/beats_blstm_4.pkl
madmom/models/beats/2015/beats_blstm_5.pkl
madmom/models/beats/2015/beats_blstm_6.pkl
madmom/models/beats/2015/beats_blstm_7.pkl
madmom/models/beats/2015/beats_blstm_8.pkl
madmom/models/beats/2016/beats_lstm_1.pkl
madmom/models/beats/2016/beats_lstm_2.pkl
madmom/models/beats/2016/beats_lstm_3.pkl
madmom/models/beats/2016/beats_lstm_4.pkl
