Metadata-Version: 1.1
Name: madmom
Version: 0.16
Summary: Python audio signal processing library
Home-page: https://github.com/CPJKU/madmom
Author: Department of Computational Perception, Johannes Kepler University, Linz, Austria and Austrian Research Institute for Artificial Intelligence (OFAI), Vienna, Austria
Author-email: madmom-users@googlegroups.com
License: BSD, CC BY-NC-SA
Platform: UNKNOWN
Classifier: Development Status :: 3 - Alpha
Classifier: Programming Language :: Python :: 2.7
Classifier: Programming Language :: Python :: 3.5
Classifier: Programming Language :: Python :: 3.6
Classifier: Programming Language :: Python :: 3.7
Classifier: Environment :: Console
Classifier: License :: OSI Approved :: BSD License
Classifier: License :: Free for non-commercial use
Classifier: Topic :: Multimedia :: Sound/Audio :: Analysis
Classifier: Topic :: Scientific/Engineering :: Artificial Intelligence
